{
  "nombre_producto": "RB-660HB",
  "nombre_ia": "RB-660HB Auriculares Inalámbricos Bluetooth con hasta 12 Horas de Reproducción",
  "referencia": "rb-660hb",
  "descripciones_originales": [
    "Auriculares inalámbricos Bluetooth con hasta 12 horas de reproducción",
    "Auriculares inalámbricos Bluetooth con hasta 12 horas de reproducción",
    "Auriculares inalámbricos Bluetooth con hasta 12 horas de reproducción"
  ],
  "precio_original": 120000,
  "precio_final": 192000,
  "descripcion_ia": "Auriculares inalámbricos Bluetooth RB-660HB diseñados para ofrecer una experiencia de audio sin interrupciones. Con hasta 12 horas de reproducción continua, son ideales para largas sesiones de música, llamadas o entretenimiento. Su tecnología Bluetooth permite una conexión estable y fácil con dispositivos compatibles, asegurando una calidad de sonido óptima. Perfectos para uso diario, viajes o ejercicio, estos auriculares ofrecen libertad y comodidad. Su diseño ergonómico se adapta a la forma de la oreja, proporcionando un ajuste seguro y confortable. Compatibles con la mayoría de dispositivos Bluetooth, son una excelente opción para aquellos que buscan disfrutar de su música favorita sin las limitaciones de cables.",
  "imagenes": [
    "C:\\Users\\h\\Downloads\\ecomerce\\e-comerce\\public\\images\\remax\\246_rb-660hb.png",
    "C:\\Users\\h\\Downloads\\ecomerce\\e-comerce\\public\\images\\remax\\247_rb-660hb.png",
    "C:\\Users\\h\\Downloads\\ecomerce\\e-comerce\\public\\images\\remax\\248_rb-660hb.png"
  ]
}