{
  "nombre_producto": "U187-C30W",
  "nombre_ia": "U187-C30W Cargador Rápido 30W con Tecnología GAN para iPhone y Android",
  "referencia": "u187-c30w",
  "descripciones_originales": [
    "Cargador de 30W con tecnología GAN para iPhone y Android",
    "Cargador de 30W con tecnología GAN para iPhone y Android",
    "Cargador de 30W con tecnología GAN para iPhone y Android"
  ],
  "precio_original": 40000,
  "precio_final": 64000,
  "descripcion_ia": "Cargador rápido de 30W con tecnología GAN compatible con dispositivos iPhone y Android. Diseñado para ofrecer una carga eficiente y segura, este cargador utiliza la avanzada tecnología GAN para minimizar el tamaño y maximizar el rendimiento. Ideal para usuarios que buscan una solución de carga rápida y fiable para sus dispositivos móviles. Características principales: Tecnología GAN para una mayor eficiencia y menor tamaño, compatible con iPhone y Android, cargador rápido de 30W.",
  "imagenes": [
    "C:\\Users\\h\\Downloads\\ecomerce\\e-comerce\\public\\images\\remax\\033_U187-C30W.png",
    "C:\\Users\\h\\Downloads\\ecomerce\\e-comerce\\public\\images\\remax\\034_U187-C30W.png",
    "C:\\Users\\h\\Downloads\\ecomerce\\e-comerce\\public\\images\\remax\\035_U187-C30W.png"
  ]
}